package_test/__init__.py
package_test/add.py
package_test/mul.py
math_package_vbi-0.1.0.dist-info/METADATA
math_package_vbi-0.1.0.dist-info/WHEEL
math_package_vbi-0.1.0.dist-info/top_level.txt
math_package_vbi-0.1.0.dist-info/RECORD
