Metadata-Version: 2.4
Name: math_package_vbi
Version: 0.1.0
Summary: A simple math package for addition and multiplication
Home-page: https://github.com/yourusername/package_test
Author: LeeMinHoon
Author-email: leminhhung19062003@gmail.com
Classifier: Programming Language :: Python :: 3
Classifier: License :: OSI Approved :: MIT License
Classifier: Operating System :: OS Independent
Requires-Python: >=3.6
Dynamic: author
Dynamic: author-email
Dynamic: classifier
Dynamic: description-content-type
Dynamic: home-page
Dynamic: requires-python
Dynamic: summary
